LICENSE
MANIFEST.in
README.rst
requirements.txt
setup.cfg
setup.py
docs/source/api.rst
docs/source/details.rst
docs/source/developer.rst
docs/source/filesystems.rst
docs/source/index.rst
docs/source/install.rst
docs/source/quickstart.rst
fastparquet/__init__.py
fastparquet/api.py
fastparquet/compression.py
fastparquet/converted_types.py
fastparquet/core.py
fastparquet/dataframe.py
fastparquet/encoding.py
fastparquet/parquet.thrift
fastparquet/schema.py
fastparquet/speedups.c
fastparquet/speedups.pyx
fastparquet/thrift_structures.py
fastparquet/util.py
fastparquet/writer.py
fastparquet/benchmarks/columns.py
fastparquet/parquet_thrift/__init__.py
fastparquet/parquet_thrift/parquet/__init__.py
fastparquet/parquet_thrift/parquet/constants.py
fastparquet/parquet_thrift/parquet/ttypes.py
fastparquet/test/__init__.py
fastparquet/test/test_api.py
fastparquet/test/test_aroundtrips.py
fastparquet/test/test_compression.py
fastparquet/test/test_converted_types.py
fastparquet/test/test_dataframe.py
fastparquet/test/test_encoding.py
fastparquet/test/test_output.py
fastparquet/test/test_partition_filters_specialstrings.py
fastparquet/test/test_read.py
fastparquet/test/test_speedups.py
fastparquet/test/test_thrift_structures.py
fastparquet/test/test_util.py
fastparquet/test/test_with_n.py
fastparquet/test/util.py
workbenchdata_fastparquet.egg-info/PKG-INFO
workbenchdata_fastparquet.egg-info/SOURCES.txt
workbenchdata_fastparquet.egg-info/dependency_links.txt
workbenchdata_fastparquet.egg-info/requires.txt
workbenchdata_fastparquet.egg-info/top_level.txt